{
  "amount": "7499",
  "courses": [
    2109,
    2110,
    2111
  ],
  "description": "<p>This major provides students with the capabilities to design effective marketing strategies while considering competitors, the economic environment, and business strategy. In doing so, we follow a customer-centric approach to marketing based on understanding customers and how they drive firm value.</p>",
  "certificate_issuer": "vignan_hs.png",
  "key_major_takeaways": [
    "Channel Management",
    "Product",
    "Pricing",
    "Place",
    "Promotions"
  ],
  "certificate_issuer_name": "Vignan (Deemed to be University)"
}